q2sfx/__init__.py
q2sfx/__main__.py
q2sfx/assets/go.mod
q2sfx/assets/main.go
q2sfx/builder.py
q2sfx/version.py
q2sfx-0.1.8.dist-info/entry_points.txt
q2sfx-0.1.8.dist-info/METADATA
q2sfx-0.1.8.dist-info/WHEEL
q2sfx-0.1.8.dist-info/RECORD
