Metadata-Version: 2.1
Name: q2sfx
Version: 0.1.8
Summary: Python-to-exe SFX builder using PyInstaller
License: MIT
Keywords: pyinstaller,sfx,installer
Author: Andrei Puchko
Author-email: andrei.puchko@gmx.de
Requires-Python: >=3.8.1,<3.13
Classifier: License :: OSI Approved :: MIT License
Classifier: Programming Language :: Python :: 3
Classifier: Programming Language :: Python :: 3.9
Classifier: Programming Language :: Python :: 3.10
Classifier: Programming Language :: Python :: 3.11
Requires-Dist: pyinstaller (>=6.0.0,<7.0.0)
